Metadata-Version: 2.1
Name: pemi
Version: 0.5.10
Summary: Pemi - Python Extract Modify Integrate
Home-page: https://github.com/inside-track/pemi
Author: Sterling Paramore
Author-email: sterling.paramore@insidetrack.com
License: MIT
Keywords: etl data workflows
Platform: UNKNOWN
Classifier: Development Status :: 3 - Alpha
Classifier: Intended Audience :: Developers
Classifier: Topic :: Software Development :: Libraries :: Python Modules
Classifier: License :: OSI Approved :: MIT License
Classifier: Programming Language :: Python :: 3
Classifier: Programming Language :: Python :: 3.6
Requires-Python: >=3
Provides-Extra: dev
Provides-Extra: test
